{"Img Captured 114.JPG198933":{"filename":"Img Captured 114.JPG","size":198933,"regions":[{"shape_attributes":{"name":"polygon","all_points_x":[616,594,610,613,626,650,670,686,695,678,640,614],"all_points_y":[630,602,583,547,519,520,529,549,594,637,645,629]},"region_attributes":{"name":"not_defined","type":"unknown","image_quality":{"good":true,"frontal":true,"good_illumination":true},"shape":"polygon"}},{"shape_attributes":{"name":"polygon","all_points_x":[991,983,1001,1020,987,1004,1038,1070,1076,1056,1044,1004,993],"all_points_y":[504,480,467,455,425,387,382,408,455,519,540,540,517]},"region_attributes":{"name":"not_defined","type":"unknown","image_quality":{"good":true,"frontal":true,"good_illumination":true},"shape":"polygon"}},{"shape_attributes":{"name":"polygon","all_points_x":[786,801,778,772,788,804,818,832,832,808,799,784],"all_points_y":[404,378,372,354,338,351,361,378,404,418,418,401]},"region_attributes":{"name":"not_defined","type":"unknown","image_quality":{"good":true,"frontal":true,"good_illumination":true},"shape":"polygon"}},{"shape_attributes":{"name":"polygon","all_points_x":[395,384,387,398,402,392],"all_points_y":[431,418,398,410,421,431]},"region_attributes":{"name":"not_defined","type":"unknown","image_quality":{"good":true,"frontal":true,"good_illumination":true},"shape":"polygon"}},{"shape_attributes":{"name":"polygon","all_points_x":[444,440,440,461,460,463,448],"all_points_y":[563,547,534,539,553,566,564]},"region_attributes":{"name":"not_defined","type":"unknown","image_quality":{"good":true,"frontal":true,"good_illumination":true},"shape":"polygon"}},{"shape_attributes":{"name":"polygon","all_points_x":[607,607,623,635,630,622,610,606],"all_points_y":[281,262,259,272,285,296,296,289]},"region_attributes":{"name":"not_defined","type":"unknown","image_quality":{"good":true,"frontal":true,"good_illumination":true},"shape":"polygon"}},{"shape_attributes":{"name":"polygon","all_points_x":[904,892,879,912,937,951,953,944,905,901,894],"all_points_y":[298,292,268,251,256,274,295,304,302,307,291]},"region_attributes":{"name":"not_defined","type":"unknown","image_quality":{"good":true,"frontal":true,"good_illumination":true},"shape":"polygon"}},{"shape_attributes":{"name":"polygon","all_points_x":[892,892,882,861,879,871,888,902,940,951,957,954,942,930,924,905,885],"all_points_y":[232,209,231,221,196,175,156,152,158,176,201,225,235,244,233,244,233]},"region_attributes":{"name":"not_defined","type":"unknown","image_quality":{"good":true,"frontal":true,"good_illumination":true},"shape":"polygon"}},{"shape_attributes":{"name":"polygon","all_points_x":[702,688,692,670,683,699,712,712,725,736,732,728,713,708],"all_points_y":[185,183,163,146,126,107,116,120,116,136,155,162,162,180]},"region_attributes":{"name":"not_defined","type":"unknown","image_quality":{"good":true,"frontal":true,"good_illumination":true},"shape":"polygon"}},{"shape_attributes":{"name":"polygon","all_points_x":[725,723,709,728,739,732,726],"all_points_y":[236,213,205,192,213,233,233]},"region_attributes":{"name":"not_defined","type":"unknown","image_quality":{"good":true,"frontal":true,"good_illumination":true},"shape":"polygon"}}],"file_attributes":{"caption":"","public_domain":"no","image_url":""}},"Img Captured 113.JPG347671":{"filename":"Img Captured 113.JPG","size":347671,"regions":[{"shape_attributes":{"name":"polygon","all_points_x":[827,819,813,797,811,833,877,905,915,911,896,867,845,829,820,833],"all_points_y":[285,279,257,231,194,184,184,191,222,253,281,298,292,286,284,278]},"region_attributes":{"name":"not_defined","type":"unknown","image_quality":{"good":true,"frontal":true,"good_illumination":true},"shape":"polygon"}},{"shape_attributes":{"name":"polygon","all_points_x":[899,883,899,928,944,946,934,912,892,884,884,884],"all_points_y":[419,387,370,360,374,400,419,424,409,402,392,389]},"region_attributes":{"name":"not_defined","type":"unknown","image_quality":{"good":true,"frontal":true,"good_illumination":true},"shape":"polygon"}},{"shape_attributes":{"name":"polygon","all_points_x":[721,702,715,726,741,748,748,735,716],"all_points_y":[459,447,434,418,419,440,450,459,459]},"region_attributes":{"name":"not_defined","type":"unknown","image_quality":{"good":true,"frontal":true,"good_illumination":true},"shape":"polygon"}},{"shape_attributes":{"name":"polygon","all_points_x":[1083,1092,1114,1124,1118,1099,1067],"all_points_y":[617,598,596,617,636,647,634]},"region_attributes":{"name":"not_defined","type":"unknown","image_quality":{"good":true,"frontal":true,"good_illumination":true},"shape":"polygon"}},{"shape_attributes":{"name":"polygon","all_points_x":[1054,1063,1079,1096,1109,1115,1096,1074,1052],"all_points_y":[373,351,338,346,355,373,390,389,373]},"region_attributes":{"name":"not_defined","type":"unknown","image_quality":{"good":true,"frontal":true,"good_illumination":true},"shape":"polygon"}},{"shape_attributes":{"name":"polygon","all_points_x":[1194,1216,1238,1241,1241,1229,1210,1194],"all_points_y":[403,374,371,392,411,427,427,412]},"region_attributes":{"name":"not_defined","type":"unknown","image_quality":{"good":true,"frontal":true,"good_illumination":true},"shape":"polygon"}},{"shape_attributes":{"name":"polygon","all_points_x":[1320,1329,1352,1371,1386,1386,1378,1367,1345,1320,1320],"all_points_y":[485,465,444,436,452,474,494,510,523,504,488]},"region_attributes":{"name":"not_defined","type":"unknown","image_quality":{"good":true,"frontal":true,"good_illumination":true},"shape":"polygon"}},{"shape_attributes":{"name":"polygon","all_points_x":[1400,1428,1450,1478,1488,1491,1478,1457,1435,1409,1400],"all_points_y":[542,531,514,512,536,563,585,599,602,583,541]},"region_attributes":{"name":"not_defined","type":"unknown","image_quality":{"good":true,"frontal":true,"good_illumination":true},"shape":"polygon"}},{"shape_attributes":{"name":"polygon","all_points_x":[1352,1352,1365,1389,1402,1402,1403,1406,1399,1378,1361,1352],"all_points_y":[180,158,145,133,137,165,184,199,202,203,196,183]},"region_attributes":{"name":"not_defined","type":"unknown","image_quality":{"good":true,"frontal":true,"good_illumination":true},"shape":"polygon"}}],"file_attributes":{"caption":"","public_domain":"no","image_url":""}},"Img Captured 112.JPG192376":{"filename":"Img Captured 112.JPG","size":192376,"regions":[{"shape_attributes":{"name":"polygon","all_points_x":[600,590,575,555,568,585,606,628,650,675,695,700,691,680,648,626],"all_points_y":[329,293,275,253,246,258,256,244,237,231,259,282,309,335,350,348]},"region_attributes":{"name":"not_defined","type":"unknown","image_quality":{"good":true,"frontal":true,"good_illumination":true},"shape":"polygon"}},{"shape_attributes":{"name":"polygon","all_points_x":[719,729,732,724,713,711],"all_points_y":[265,260,253,246,249,260]},"region_attributes":{"name":"not_defined","type":"unknown","image_quality":{"good":true,"frontal":true,"good_illumination":true},"shape":"polygon"}},{"shape_attributes":{"name":"polygon","all_points_x":[789,805,817,812,792,783,783],"all_points_y":[266,268,249,236,240,252,263]},"region_attributes":{"name":"not_defined","type":"unknown","image_quality":{"good":true,"frontal":true,"good_illumination":true},"shape":"polygon"}},{"shape_attributes":{"name":"polygon","all_points_x":[732,749,765,765,755,742,730,730],"all_points_y":[307,310,297,268,258,255,277,306]},"region_attributes":{"name":"not_defined","type":"unknown","image_quality":{"good":true,"frontal":true,"good_illumination":true},"shape":"polygon"}},{"shape_attributes":{"name":"polygon","all_points_x":[716,730,733,719,708,708,717],"all_points_y":[366,359,344,341,351,360,367]},"region_attributes":{"name":"not_defined","type":"unknown","image_quality":{"good":true,"frontal":true,"good_illumination":true},"shape":"polygon"}},{"shape_attributes":{"name":"polygon","all_points_x":[694,685,672,686,692],"all_points_y":[379,375,388,395,376]},"region_attributes":{"name":"not_defined","type":"unknown","image_quality":{"good":true,"frontal":true,"good_illumination":true},"shape":"polygon"}},{"shape_attributes":{"name":"polygon","all_points_x":[793,789,798,815,825,821,815,799],"all_points_y":[379,359,335,325,340,357,380,385]},"region_attributes":{"name":"not_defined","type":"unknown","image_quality":{"good":true,"frontal":true,"good_illumination":true},"shape":"polygon"}},{"shape_attributes":{"name":"polygon","all_points_x":[799,821,834,834,853,871,863,837,825,802],"all_points_y":[446,421,410,379,364,386,410,426,452,455]},"region_attributes":{"name":"not_defined","type":"unknown","image_quality":{"good":true,"frontal":true,"good_illumination":true},"shape":"polygon"}},{"shape_attributes":{"name":"polygon","all_points_x":[719,736,748,755,740,719],"all_points_y":[596,571,582,596,603,590]},"region_attributes":{"name":"not_defined","type":"unknown","image_quality":{"good":true,"frontal":true,"good_illumination":true},"shape":"polygon"}},{"shape_attributes":{"name":"polygon","all_points_x":[770,798,814,808,792,773,758,752,758,776,793,801],"all_points_y":[577,569,550,533,522,534,546,560,577,577,571,572]},"region_attributes":{"name":"not_defined","type":"unknown","image_quality":{"good":true,"frontal":true,"good_illumination":true},"shape":"polygon"}},{"shape_attributes":{"name":"polygon","all_points_x":[814,811,820,830,831,820,812],"all_points_y":[700,685,676,685,700,707,688]},"region_attributes":{"name":"not_defined","type":"unknown","image_quality":{"good":true,"frontal":true,"good_illumination":true},"shape":"polygon"}}],"file_attributes":{"caption":"","public_domain":"no","image_url":""}},"Img Captured 111.JPG172090":{"filename":"Img Captured 111.JPG","size":172090,"regions":[{"shape_attributes":{"name":"polygon","all_points_x":[539,548,549,562,589,608,613,605,578,557,536],"all_points_y":[497,489,463,441,437,448,478,513,519,519,498]},"region_attributes":{"name":"not_defined","type":"unknown","image_quality":{"good":true,"frontal":true,"good_illumination":true},"shape":"polygon"}},{"shape_attributes":{"name":"polygon","all_points_x":[571,589,612,581,577,608,640,681,704,716,703,672,668,568],"all_points_y":[795,786,784,765,738,711,676,679,703,739,774,793,802,802]},"region_attributes":{"name":"not_defined","type":"unknown","image_quality":{"good":true,"frontal":true,"good_illumination":true},"shape":"polygon"}},{"shape_attributes":{"name":"polygon","all_points_x":[508,502,516,535,543,530,523,502],"all_points_y":[336,321,311,320,343,356,361,358]},"region_attributes":{"name":"not_defined","type":"unknown","image_quality":{"good":true,"frontal":true,"good_illumination":true},"shape":"polygon"}},{"shape_attributes":{"name":"polygon","all_points_x":[297,301,251,257,288,380,441,462,447,405,349,318,297],"all_points_y":[391,362,308,260,212,226,257,308,356,390,424,428,394]},"region_attributes":{"name":"not_defined","type":"unknown","image_quality":{"good":true,"frontal":true,"good_illumination":true},"shape":"polygon"}},{"shape_attributes":{"name":"polygon","all_points_x":[822,822,837,853,844,841,828,827],"all_points_y":[510,489,475,486,504,520,530,519]},"region_attributes":{"name":"not_defined","type":"unknown","image_quality":{"good":true,"frontal":true,"good_illumination":true},"shape":"polygon"}},{"shape_attributes":{"name":"polygon","all_points_x":[930,926,938,964,977,963],"all_points_y":[450,434,410,410,432,457]},"region_attributes":{"name":"not_defined","type":"unknown","image_quality":{"good":true,"frontal":true,"good_illumination":true},"shape":"polygon"}},{"shape_attributes":{"name":"polygon","all_points_x":[939,932,970,1033,1097,1115,1133,1133,1122,1093,1065,1001,983,961,941],"all_points_y":[365,327,267,234,223,213,241,285,342,372,386,377,390,397,374]},"region_attributes":{"name":"not_defined","type":"unknown","image_quality":{"good":true,"frontal":true,"good_illumination":true},"shape":"polygon"}},{"shape_attributes":{"name":"polygon","all_points_x":[597,622,622,621,640,668,672,685,679,717,746,749,758,738,697,649,627,606,599,599],"all_points_y":[225,210,200,165,149,139,117,105,74,60,73,101,149,212,245,251,253,253,242,228]},"region_attributes":{"name":"not_defined","type":"unknown","image_quality":{"good":true,"frontal":true,"good_illumination":true},"shape":"polygon"}},{"shape_attributes":{"name":"polygon","all_points_x":[892,891,907,920,932,932,910,898,897],"all_points_y":[127,105,95,98,107,121,129,131,127]},"region_attributes":{"name":"not_defined","type":"unknown","image_quality":{"good":true,"frontal":true,"good_illumination":true},"shape":"polygon"}}],"file_attributes":{"caption":"","public_domain":"no","image_url":""}},"Img Captured 110.JPG169520":{"filename":"Img Captured 110.JPG","size":169520,"regions":[{"shape_attributes":{"name":"polygon","all_points_x":[409,397,396,409,424,429,426,419,415],"all_points_y":[106,98,84,77,79,90,102,105,108]},"region_attributes":{"name":"not_defined","type":"unknown","image_quality":{"good":true,"frontal":true,"good_illumination":true},"shape":"polygon"}},{"shape_attributes":{"name":"polygon","all_points_x":[392,383,374,388,408,410,409],"all_points_y":[190,184,179,170,168,180,189]},"region_attributes":{"name":"not_defined","type":"unknown","image_quality":{"good":true,"frontal":true,"good_illumination":true},"shape":"polygon"}},{"shape_attributes":{"name":"polygon","all_points_x":[318,330,338,336,322],"all_points_y":[183,173,180,191,186]},"region_attributes":{"name":"not_defined","type":"unknown","image_quality":{"good":true,"frontal":true,"good_illumination":true},"shape":"polygon"}},{"shape_attributes":{"name":"polygon","all_points_x":[279,279,286,294,297,298,292,285],"all_points_y":[534,524,511,507,517,528,542,547]},"region_attributes":{"name":"not_defined","type":"unknown","image_quality":{"good":true,"frontal":true,"good_illumination":true},"shape":"polygon"}},{"shape_attributes":{"name":"polygon","all_points_x":[337,333,336,345,352,366,369,373,373,355,343,334,338],"all_points_y":[525,517,503,490,490,492,501,510,531,542,536,534,523]},"region_attributes":{"name":"not_defined","type":"unknown","image_quality":{"good":true,"frontal":true,"good_illumination":true},"shape":"polygon"}},{"shape_attributes":{"name":"polygon","all_points_x":[479,490,501,508,510,501,479,479],"all_points_y":[582,572,572,579,592,605,597,586]},"region_attributes":{"name":"not_defined","type":"unknown","image_quality":{"good":true,"frontal":true,"good_illumination":true},"shape":"polygon"}},{"shape_attributes":{"name":"polygon","all_points_x":[484,483,485,500,513,504,489,472,455,470,483,501,515,523,534,545,551,555,556,558,562,564,558,539,527,523,509,486],"all_points_y":[551,541,532,520,519,505,489,481,466,442,434,434,432,427,426,436,448,467,476,492,503,530,553,556,551,548,561,553]},"region_attributes":{"name":"not_defined","type":"unknown","image_quality":{"good":true,"frontal":true,"good_illumination":true},"shape":"polygon"}},{"shape_attributes":{"name":"polygon","all_points_x":[501,518,526,529,522,510,501,501],"all_points_y":[377,363,372,382,393,401,398,377]},"region_attributes":{"name":"not_defined","type":"unknown","image_quality":{"good":true,"frontal":true,"good_illumination":true},"shape":"polygon"}},{"shape_attributes":{"name":"polygon","all_points_x":[385,385,388,388,409,419,422,419,409,394,386],"all_points_y":[385,382,395,415,418,417,407,398,390,387,383]},"region_attributes":{"name":"not_defined","type":"unknown","image_quality":{"good":true,"frontal":true,"good_illumination":true},"shape":"polygon"}},{"shape_attributes":{"name":"polygon","all_points_x":[603,597,596,614,618,634,639,648,649,625,615],"all_points_y":[472,458,435,409,406,420,431,442,454,471,486]},"region_attributes":{"name":"not_defined","type":"unknown","image_quality":{"good":true,"frontal":true,"good_illumination":true},"shape":"polygon"}},{"shape_attributes":{"name":"polygon","all_points_x":[678,676,681,694,704,705,698,683],"all_points_y":[530,522,511,506,513,525,534,534]},"region_attributes":{"name":"not_defined","type":"unknown","image_quality":{"good":true,"frontal":true,"good_illumination":true},"shape":"polygon"}},{"shape_attributes":{"name":"polygon","all_points_x":[728,734,742,755,766,763,756,737],"all_points_y":[522,510,506,501,509,524,536,531]},"region_attributes":{"name":"not_defined","type":"unknown","image_quality":{"good":true,"frontal":true,"good_illumination":true},"shape":"polygon"}},{"shape_attributes":{"name":"polygon","all_points_x":[673,667,656,653,657,664,670,674,672,678,682,680],"all_points_y":[153,144,147,142,132,120,114,134,138,138,144,153]},"region_attributes":{"name":"not_defined","type":"unknown","image_quality":{"good":true,"frontal":true,"good_illumination":true},"shape":"polygon"}},{"shape_attributes":{"name":"polygon","all_points_x":[762,774,783,785,795,791,815,838,854,862,883,880,884,873,851,812,800,783,777],"all_points_y":[292,285,281,271,274,256,244,226,218,214,228,245,268,308,322,321,310,296,296]},"region_attributes":{"name":"not_defined","type":"unknown","image_quality":{"good":true,"frontal":true,"good_illumination":true},"shape":"polygon"}},{"shape_attributes":{"name":"polygon","all_points_x":[948,963,974,990,1005,1019,1020,1008,992,947],"all_points_y":[315,300,283,269,272,290,310,327,335,313]},"region_attributes":{"name":"not_defined","type":"unknown","image_quality":{"good":true,"frontal":true,"good_illumination":true},"shape":"polygon"}},{"shape_attributes":{"name":"polygon","all_points_x":[918,933,946,944,934,924,915],"all_points_y":[436,442,437,428,415,422,425]},"region_attributes":{"name":"not_defined","type":"unknown","image_quality":{"good":true,"frontal":true,"good_illumination":true},"shape":"polygon"}},{"shape_attributes":{"name":"polygon","all_points_x":[882,885,915,934,948,951,947,931,907,903,883],"all_points_y":[479,472,451,448,462,486,509,506,495,486,484]},"region_attributes":{"name":"not_defined","type":"unknown","image_quality":{"good":true,"frontal":true,"good_illumination":true},"shape":"polygon"}},{"shape_attributes":{"name":"polygon","all_points_x":[929,924,930,945,967,982,975,961,937],"all_points_y":[542,539,522,514,502,518,539,551,548]},"region_attributes":{"name":"not_defined","type":"unknown","image_quality":{"good":true,"frontal":true,"good_illumination":true},"shape":"polygon"}},{"shape_attributes":{"name":"polygon","all_points_x":[1029,1040,1049,1060,1047,1029,1024],"all_points_y":[610,604,604,622,637,632,625]},"region_attributes":{"name":"not_defined","type":"unknown","image_quality":{"good":true,"frontal":true,"good_illumination":true},"shape":"polygon"}},{"shape_attributes":{"name":"polygon","all_points_x":[1063,1069,1075,1087,1093,1083,1072],"all_points_y":[469,462,452,454,468,480,483]},"region_attributes":{"name":"not_defined","type":"unknown","image_quality":{"good":true,"frontal":true,"good_illumination":true},"shape":"polygon"}},{"shape_attributes":{"name":"polygon","all_points_x":[1092,1099,1103,1110,1154,1150,1125,1095],"all_points_y":[447,426,415,406,373,473,474,454]},"region_attributes":{"name":"not_defined","type":"unknown","image_quality":{"good":true,"frontal":true,"good_illumination":true},"shape":"polygon"}},{"shape_attributes":{"name":"polygon","all_points_x":[643,643,659,670,688,706,715,721,714,688,650,637,644],"all_points_y":[699,695,679,669,643,647,663,680,709,728,716,712,695]},"region_attributes":{"name":"not_defined","type":"unknown","image_quality":{"good":true,"frontal":true,"good_illumination":true},"shape":"polygon"}},{"shape_attributes":{"name":"polygon","all_points_x":[848,848,860,871,884,887,890,883,861],"all_points_y":[650,631,618,616,619,633,641,660,658]},"region_attributes":{"name":"not_defined","type":"unknown","image_quality":{"good":true,"frontal":true,"good_illumination":true},"shape":"polygon"}},{"shape_attributes":{"name":"polygon","all_points_x":[850,865,880,886,877,862,844,850],"all_points_y":[765,765,769,784,796,802,783,761]},"region_attributes":{"name":"not_defined","type":"unknown","image_quality":{"good":true,"frontal":true,"good_illumination":true},"shape":"polygon"}},{"shape_attributes":{"name":"polygon","all_points_x":[1087,1083,1090,1099,1114,1122,1113,1087,1078],"all_points_y":[712,702,688,682,693,713,730,735,728]},"region_attributes":{"name":"not_defined","type":"unknown","image_quality":{"good":true,"frontal":true,"good_illumination":true},"shape":"polygon"}},{"shape_attributes":{"name":"polygon","all_points_x":[1097,1093,1102,1121,1124,1111,1102],"all_points_y":[783,765,754,763,778,792,788]},"region_attributes":{"name":"not_defined","type":"unknown","image_quality":{"good":true,"frontal":true,"good_illumination":true},"shape":"polygon"}},{"shape_attributes":{"name":"polygon","all_points_x":[1089,1101,1113,1109,1089],"all_points_y":[532,523,530,540,531]},"region_attributes":{"name":"not_defined","type":"unknown","image_quality":{"good":true,"frontal":true,"good_illumination":true},"shape":"polygon"}},{"shape_attributes":{"name":"polygon","all_points_x":[752,758,768,771,763],"all_points_y":[694,677,677,691,705]},"region_attributes":{"name":"not_defined","type":"unknown","image_quality":{"good":true,"frontal":true,"good_illumination":true},"shape":"polygon"}}],"file_attributes":{"caption":"","public_domain":"no","image_url":""}},"Img Captured 109.JPG149958":{"filename":"Img Captured 109.JPG","size":149958,"regions":[{"shape_attributes":{"name":"polygon","all_points_x":[728,671,626,596,559,534,536,568,613,660,696,734,790,826,850,874,882,874,847,807,768,733],"all_points_y":[518,502,476,453,420,391,355,324,295,286,277,247,229,229,255,308,372,435,486,517,534,520]},"region_attributes":{"name":"not_defined","type":"unknown","image_quality":{"good":true,"frontal":true,"good_illumination":true},"shape":"polygon"}},{"shape_attributes":{"name":"polygon","all_points_x":[978,972,988,1006,1058,1088,1112,1139,1146,1123,1099,1035,993],"all_points_y":[526,488,454,420,399,393,412,439,485,547,577,580,559]},"region_attributes":{"name":"not_defined","type":"unknown","image_quality":{"good":true,"frontal":true,"good_illumination":true},"shape":"polygon"}},{"shape_attributes":{"name":"polygon","all_points_x":[1212,1223,1236,1283,1304,1321,1324,1302,1261,1217],"all_points_y":[441,412,400,377,380,407,441,467,479,455]},"region_attributes":{"name":"not_defined","type":"unknown","image_quality":{"good":true,"frontal":true,"good_illumination":true},"shape":"polygon"}},{"shape_attributes":{"name":"polygon","all_points_x":[1307,1302,1321,1347,1343,1343,1320,1305],"all_points_y":[613,587,584,594,620,635,648,639]},"region_attributes":{"name":"not_defined","type":"unknown","image_quality":{"good":true,"frontal":true,"good_illumination":true},"shape":"polygon"}},{"shape_attributes":{"name":"polygon","all_points_x":[1193,1207,1231,1254,1244,1220,1194,1182],"all_points_y":[670,660,645,667,724,724,715,702]},"region_attributes":{"name":"not_defined","type":"unknown","image_quality":{"good":true,"frontal":true,"good_illumination":true},"shape":"polygon"}},{"shape_attributes":{"name":"polygon","all_points_x":[1166,1153,1149,1152,1169,1185,1182,1180],"all_points_y":[693,704,715,721,733,723,708,698]},"region_attributes":{"name":"not_defined","type":"unknown","image_quality":{"good":true,"frontal":true,"good_illumination":true},"shape":"polygon"}},{"shape_attributes":{"name":"polygon","all_points_x":[809,812,839,860,886,905,914,918,892,873,838,804],"all_points_y":[666,658,639,616,604,613,632,667,693,695,692,658]},"region_attributes":{"name":"not_defined","type":"unknown","image_quality":{"good":true,"frontal":true,"good_illumination":true},"shape":"polygon"}},{"shape_attributes":{"name":"polygon","all_points_x":[375,391,400,423,448,457,488,504,507,502,482,445,409,382,374,365,361],"all_points_y":[521,511,485,453,428,417,426,455,495,536,568,580,577,563,546,547,549]},"region_attributes":{"name":"not_defined","type":"unknown","image_quality":{"good":true,"frontal":true,"good_illumination":true},"shape":"polygon"}},{"shape_attributes":{"name":"polygon","all_points_x":[209,239,258,272,279,276,258,218,212],"all_points_y":[448,435,406,375,333,289,251,236,245]},"region_attributes":{"name":"not_defined","type":"unknown","image_quality":{"good":true,"frontal":true,"good_illumination":true},"shape":"polygon"}},{"shape_attributes":{"name":"polygon","all_points_x":[791,759,756,762,774,819,829,857,883,889,877,858,822],"all_points_y":[197,168,139,109,98,96,121,133,146,163,193,215,220]},"region_attributes":{"name":"not_defined","type":"unknown","image_quality":{"good":true,"frontal":true,"good_illumination":true},"shape":"polygon"}}],"file_attributes":{"caption":"","public_domain":"no","image_url":""}},"Img Captured 108.JPG175660":{"filename":"Img Captured 108.JPG","size":175660,"regions":[{"shape_attributes":{"name":"polygon","all_points_x":[645,677,702,728,697,719,741,772,798,798,810,800,772,745,697,658,647],"all_points_y":[298,263,222,224,183,151,132,137,155,191,225,276,320,335,336,329,326]},"region_attributes":{"name":"not_defined","type":"unknown","image_quality":{"good":true,"frontal":true,"good_illumination":true},"shape":"polygon"}},{"shape_attributes":{"name":"polygon","all_points_x":[930,944,969,1007,1030,1041,1023,985,952],"all_points_y":[254,224,210,213,234,262,294,297,289]},"region_attributes":{"name":"not_defined","type":"unknown","image_quality":{"good":true,"frontal":true,"good_illumination":true},"shape":"polygon"}},{"shape_attributes":{"name":"polygon","all_points_x":[449,446,457,482,512,525,514,497,472,463],"all_points_y":[630,608,589,586,592,618,640,646,643,650]},"region_attributes":{"name":"not_defined","type":"unknown","image_quality":{"good":true,"frontal":true,"good_illumination":true},"shape":"polygon"}},{"shape_attributes":{"name":"polygon","all_points_x":[573,585,609,636,650,652,652,609,570],"all_points_y":[642,609,586,585,593,618,646,668,647]},"region_attributes":{"name":"not_defined","type":"unknown","image_quality":{"good":true,"frontal":true,"good_illumination":true},"shape":"polygon"}},{"shape_attributes":{"name":"polygon","all_points_x":[642,646,665,691,719,738,747,754,754,740,702,672,637,643],"all_points_y":[696,671,649,628,650,674,693,718,741,741,745,731,702,671]},"region_attributes":{"name":"not_defined","type":"unknown","image_quality":{"good":true,"frontal":true,"good_illumination":true},"shape":"polygon"}},{"shape_attributes":{"name":"polygon","all_points_x":[775,713,723,725,721,747,775,761,775,797,808,814,851,862,902,928,937,943,965,995,1014,1044,1068,1079,1070,1057,1033,978,954,934,911,902,870,880,864,845,852,857,854,816,783,726,707],"all_points_y":[623,605,571,541,510,488,460,441,400,387,387,357,342,320,332,354,379,396,398,386,396,411,440,479,523,560,596,605,601,609,596,571,548,520,497,472,519,567,605,621,624,611,596]},"region_attributes":{"name":"not_defined","type":"unknown","image_quality":{"good":true,"frontal":true,"good_illumination":true},"shape":"polygon"}},{"shape_attributes":{"name":"polygon","all_points_x":[1209,1175,1133,1101,1087,1093,1099,1136,1155,1194,1213,1244,1280,1276,1250,1257,1248,1232,1196],"all_points_y":[696,691,696,664,645,589,564,569,620,607,571,538,533,580,604,645,680,706,693]},"region_attributes":{"name":"not_defined","type":"unknown","image_quality":{"good":true,"frontal":true,"good_illumination":true},"shape":"polygon"}}],"file_attributes":{"caption":"","public_domain":"no","image_url":""}},"Img Captured 107.JPG181983":{"filename":"Img Captured 107.JPG","size":181983,"regions":[{"shape_attributes":{"name":"polygon","all_points_x":[412,416,400,372,371,372,366,396,412,423,445,447,473,493,498,523,536,556,556,558,571,584,607,597,585,597,601,587,604,617,629,620,596,569,556,531,511,496,474,476,472,457,453],"all_points_y":[558,542,508,505,482,464,429,439,453,464,464,458,469,479,489,493,490,472,448,436,422,439,448,466,469,480,496,504,523,533,539,555,531,537,520,533,515,533,527,546,566,588,585]},"region_attributes":{"name":"not_defined","type":"unknown","image_quality":{"good":true,"frontal":true,"good_illumination":true},"shape":"polygon"}},{"shape_attributes":{"name":"polygon","all_points_x":[654,658,671,651,639,631,642,647,642,625,625,612,609,620,631,651,673,696,702,704,711,728,743,752,733,698,692,696,661],"all_points_y":[606,590,593,580,556,530,518,489,482,509,489,504,476,464,448,461,464,469,483,492,467,479,485,498,526,552,580,593,609]},"region_attributes":{"name":"not_defined","type":"unknown","image_quality":{"good":true,"frontal":true,"good_illumination":true},"shape":"polygon"}},{"shape_attributes":{"name":"polygon","all_points_x":[780,755,736,743,756,768,812,842,854,848,842,816,787,780,774],"all_points_y":[578,584,569,537,511,505,521,539,555,575,596,607,599,590,585]},"region_attributes":{"name":"not_defined","type":"unknown","image_quality":{"good":true,"frontal":true,"good_illumination":true},"shape":"polygon"}},{"shape_attributes":{"name":"polygon","all_points_x":[836,819,813,828,815,822,832,855,873,877,873,864,851,870,886,873,860,854],"all_points_y":[517,514,496,486,473,448,429,423,435,455,474,485,485,512,534,552,552,549]},"region_attributes":{"name":"not_defined","type":"unknown","image_quality":{"good":true,"frontal":true,"good_illumination":true},"shape":"polygon"}},{"shape_attributes":{"name":"polygon","all_points_x":[620,604,617,632,651,664,651,639,628],"all_points_y":[692,680,661,658,661,671,683,695,701]},"region_attributes":{"name":"not_defined","type":"unknown","image_quality":{"good":true,"frontal":true,"good_illumination":true},"shape":"polygon"}},{"shape_attributes":{"name":"polygon","all_points_x":[683,683,692,704,721,726,709,704,704,707,696,688],"all_points_y":[717,695,671,685,699,712,717,707,721,733,733,728]},"region_attributes":{"name":"not_defined","type":"unknown","image_quality":{"good":true,"frontal":true,"good_illumination":true},"shape":"polygon"}},{"shape_attributes":{"name":"polygon","all_points_x":[841,828,832,842,848,855,867,866,853,839],"all_points_y":[629,617,604,617,597,565,594,616,636,641]},"region_attributes":{"name":"not_defined","type":"unknown","image_quality":{"good":true,"frontal":true,"good_illumination":true},"shape":"polygon"}},{"shape_attributes":{"name":"polygon","all_points_x":[742,737,749,765,761,758,755,755],"all_points_y":[631,619,610,607,620,625,638,645]},"region_attributes":{"name":"not_defined","type":"unknown","image_quality":{"good":true,"frontal":true,"good_illumination":true},"shape":"polygon"}},{"shape_attributes":{"name":"polygon","all_points_x":[701,708,698,723,726,709,704],"all_points_y":[669,651,648,641,639,667,671]},"region_attributes":{"name":"not_defined","type":"unknown","image_quality":{"good":true,"frontal":true,"good_illumination":true},"shape":"polygon"}},{"shape_attributes":{"name":"polygon","all_points_x":[561,568,581,575,569,559,550,568],"all_points_y":[384,372,385,394,404,404,396,374]},"region_attributes":{"name":"not_defined","type":"unknown","image_quality":{"good":true,"frontal":true,"good_illumination":true},"shape":"polygon"}},{"shape_attributes":{"name":"polygon","all_points_x":[661,644,651,673,692,693,683,674],"all_points_y":[328,315,298,292,301,312,320,328]},"region_attributes":{"name":"not_defined","type":"unknown","image_quality":{"good":true,"frontal":true,"good_illumination":true},"shape":"polygon"}},{"shape_attributes":{"name":"polygon","all_points_x":[1023,984,953,926,947,956,981,996,1004,1026,1039,1067,1074,1099,1121,1120,1131,1123,1140,1153,1172,1174,1153,1142,1108,1079,1050,1022,1029,1009],"all_points_y":[320,307,293,272,241,213,222,223,206,201,201,200,216,204,234,255,273,279,290,309,308,350,362,385,399,382,366,358,328,315]},"region_attributes":{"name":"not_defined","type":"unknown","image_quality":{"good":true,"frontal":true,"good_illumination":true},"shape":"polygon"}},{"shape_attributes":{"name":"polygon","all_points_x":[723,717,717,733,733],"all_points_y":[323,314,302,309,318]},"region_attributes":{"name":"not_defined","type":"unknown","image_quality":{"good":true,"frontal":true,"good_illumination":true},"shape":"polygon"}},{"shape_attributes":{"name":"polygon","all_points_x":[749,746,737,728,730,761,766,746],"all_points_y":[283,292,295,283,270,273,283,285]},"region_attributes":{"name":"not_defined","type":"unknown","image_quality":{"good":true,"frontal":true,"good_illumination":true},"shape":"polygon"}},{"shape_attributes":{"name":"polygon","all_points_x":[613,591,577,588,588,593,613,625,632,636,634,631,622,607],"all_points_y":[185,185,188,159,150,133,133,149,150,180,196,201,210,184]},"region_attributes":{"name":"not_defined","type":"unknown","image_quality":{"good":true,"frontal":true,"good_illumination":true},"shape":"polygon"}},{"shape_attributes":{"name":"polygon","all_points_x":[781,781,766,762,759,778,778,774,780,799,807,812,815,836,839,816,796],"all_points_y":[220,200,177,150,134,134,153,159,177,177,174,191,200,212,231,250,247]},"region_attributes":{"name":"not_defined","type":"unknown","image_quality":{"good":true,"frontal":true,"good_illumination":true},"shape":"polygon"}},{"shape_attributes":{"name":"polygon","all_points_x":[784,774,787,800,812],"all_points_y":[328,301,299,324,336]},"region_attributes":{"name":"not_defined","type":"unknown","image_quality":{"good":true,"frontal":true,"good_illumination":true},"shape":"polygon"}},{"shape_attributes":{"name":"polygon","all_points_x":[799,788,787,800,804,806],"all_points_y":[272,269,258,251,264,270]},"region_attributes":{"name":"not_defined","type":"unknown","image_quality":{"good":true,"frontal":true,"good_illumination":true},"shape":"polygon"}},{"shape_attributes":{"name":"polygon","all_points_x":[1086,1086,1090,1057,1029,1044,1061,1090,1146,1184,1196,1197,1166,1166,1156,1082],"all_points_y":[708,679,663,657,650,701,731,750,744,740,704,683,680,717,736,709]},"region_attributes":{"name":"not_defined","type":"unknown","image_quality":{"good":true,"frontal":true,"good_illumination":true},"shape":"polygon"}},{"shape_attributes":{"name":"polygon","all_points_x":[1165,1174,1125,1102,1105,1124,1139,1161,1182,1206,1206,1200,1163],"all_points_y":[666,635,626,622,597,597,571,588,577,615,645,682,679]},"region_attributes":{"name":"not_defined","type":"unknown","image_quality":{"good":true,"frontal":true,"good_illumination":true},"shape":"polygon"}},{"shape_attributes":{"name":"polygon","all_points_x":[1228,1226,1239,1247,1254,1254,1239,1236],"all_points_y":[177,158,153,171,184,194,194,191]},"region_attributes":{"name":"not_defined","type":"unknown","image_quality":{"good":true,"frontal":true,"good_illumination":true},"shape":"polygon"}},{"shape_attributes":{"name":"polygon","all_points_x":[523,517,533,539,539,539,536],"all_points_y":[274,269,260,266,274,276,279]},"region_attributes":{"name":"not_defined","type":"unknown","image_quality":{"good":true,"frontal":true,"good_illumination":true},"shape":"polygon"}}],"file_attributes":{"caption":"","public_domain":"no","image_url":""}},"Img Captured 106.JPG135653":{"filename":"Img Captured 106.JPG","size":135653,"regions":[{"shape_attributes":{"name":"polygon","all_points_x":[424,437,463,494,516,571,617,642,677,706,734,718,697,699,702,659,646,604,560,512,468,441,421],"all_points_y":[462,440,412,379,364,333,320,311,308,317,342,381,387,415,443,469,495,526,529,528,517,504,468]},"region_attributes":{"name":"not_defined","type":"unknown","image_quality":{"good":true,"frontal":true,"good_illumination":true},"shape":"polygon"}},{"shape_attributes":{"name":"polygon","all_points_x":[355,324,332,342,379,381,383,383,383,368],"all_points_y":[516,504,484,475,468,487,498,504,519,516]},"region_attributes":{"name":"not_defined","type":"unknown","image_quality":{"good":true,"frontal":true,"good_illumination":true},"shape":"polygon"}},{"shape_attributes":{"name":"polygon","all_points_x":[292,272,267,292,319,341,335,326,320],"all_points_y":[617,604,589,564,569,586,607,621,621]},"region_attributes":{"name":"not_defined","type":"unknown","image_quality":{"good":true,"frontal":true,"good_illumination":true},"shape":"polygon"}},{"shape_attributes":{"name":"polygon","all_points_x":[335,333,348,367,392,406,415,398,368,354,330],"all_points_y":[402,379,332,322,317,360,398,419,424,419,402]},"region_attributes":{"name":"not_defined","type":"unknown","image_quality":{"good":true,"frontal":true,"good_illumination":true},"shape":"polygon"}},{"shape_attributes":{"name":"polygon","all_points_x":[528,500,507,538,573,595,588,564],"all_points_y":[620,604,571,564,564,589,623,636]},"region_attributes":{"name":"not_defined","type":"unknown","image_quality":{"good":true,"frontal":true,"good_illumination":true},"shape":"polygon"}},{"shape_attributes":{"name":"polygon","all_points_x":[786,764,775,813,862,870,870,857,824,813,794],"all_points_y":[357,319,297,294,282,301,341,374,398,390,376]},"region_attributes":{"name":"not_defined","type":"unknown","image_quality":{"good":true,"frontal":true,"good_illumination":true},"shape":"polygon"}},{"shape_attributes":{"name":"polygon","all_points_x":[887,919,937,949,933,949,940,918,934,953,962,990,1007,1039,1070,1093,1093,1085,1052,1001,947,887,874,870],"all_points_y":[466,436,379,364,332,304,289,304,284,285,295,316,357,381,387,425,437,497,539,560,560,535,522,512]},"region_attributes":{"name":"not_defined","type":"unknown","image_quality":{"good":true,"frontal":true,"good_illumination":true},"shape":"polygon"}},{"shape_attributes":{"name":"polygon","all_points_x":[1200,1200,1175,1150,1143,1191,1232,1238,1234,1237,1234],"all_points_y":[498,465,471,444,422,425,428,431,476,500,513]},"region_attributes":{"name":"not_defined","type":"unknown","image_quality":{"good":true,"frontal":true,"good_illumination":true},"shape":"polygon"}}],"file_attributes":{"caption":"","public_domain":"no","image_url":""}},"Img Captured 105.JPG170466":{"filename":"Img Captured 105.JPG","size":170466,"regions":[{"shape_attributes":{"name":"polygon","all_points_x":[1032,1016,1010,1023,1023,1036,1048,1035,1029],"all_points_y":[232,239,222,218,196,213,222,226,229]},"region_attributes":{"name":"not_defined","type":"unknown","image_quality":{"good":true,"frontal":true,"good_illumination":true},"shape":"polygon"}},{"shape_attributes":{"name":"polygon","all_points_x":[772,790,791,794,788,812,836,838,842,832,826,812,785,765,771],"all_points_y":[374,358,358,342,311,304,305,323,369,391,399,401,399,384,399]},"region_attributes":{"name":"not_defined","type":"unknown","image_quality":{"good":true,"frontal":true,"good_illumination":true},"shape":"polygon"}},{"shape_attributes":{"name":"polygon","all_points_x":[711,711,701,707,733,755,771,761,733,723],"all_points_y":[323,308,288,277,277,290,317,340,355,350]},"region_attributes":{"name":"not_defined","type":"unknown","image_quality":{"good":true,"frontal":true,"good_illumination":true},"shape":"polygon"}},{"shape_attributes":{"name":"polygon","all_points_x":[521,530,543,547,539,527,523],"all_points_y":[375,356,365,369,387,382,385]},"region_attributes":{"name":"not_defined","type":"unknown","image_quality":{"good":true,"frontal":true,"good_illumination":true},"shape":"polygon"}},{"shape_attributes":{"name":"polygon","all_points_x":[552,547,547,569,625,677,699,689,671,634,596,574,542],"all_points_y":[365,345,309,296,285,286,334,374,404,415,410,393,363]},"region_attributes":{"name":"not_defined","type":"unknown","image_quality":{"good":true,"frontal":true,"good_illumination":true},"shape":"polygon"}},{"shape_attributes":{"name":"polygon","all_points_x":[346,317,312,330,361,382,394,394,387,372,358],"all_points_y":[333,330,307,290,270,286,304,324,327,343,340]},"region_attributes":{"name":"not_defined","type":"unknown","image_quality":{"good":true,"frontal":true,"good_illumination":true},"shape":"polygon"}},{"shape_attributes":{"name":"polygon","all_points_x":[416,428,460,486,512,514,514,477,432,417,417,420],"all_points_y":[331,285,283,285,311,343,381,400,391,385,384,380]},"region_attributes":{"name":"not_defined","type":"unknown","image_quality":{"good":true,"frontal":true,"good_illumination":true},"shape":"polygon"}},{"shape_attributes":{"name":"polygon","all_points_x":[410,387,381,381,399,420,412],"all_points_y":[399,407,393,368,363,378,385]},"region_attributes":{"name":"not_defined","type":"unknown","image_quality":{"good":true,"frontal":true,"good_illumination":true},"shape":"polygon"}},{"shape_attributes":{"name":"polygon","all_points_x":[385,401,417,409,390,388,382],"all_points_y":[419,407,419,435,435,435,431]},"region_attributes":{"name":"not_defined","type":"unknown","image_quality":{"good":true,"frontal":true,"good_illumination":true},"shape":"polygon"}},{"shape_attributes":{"name":"polygon","all_points_x":[340,340,356,366,363,350],"all_points_y":[451,434,429,439,460,455]},"region_attributes":{"name":"not_defined","type":"unknown","image_quality":{"good":true,"frontal":true,"good_illumination":true},"shape":"polygon"}},{"shape_attributes":{"name":"polygon","all_points_x":[270,239,209,197,218,242,258,280,304,309,288],"all_points_y":[234,216,197,184,174,174,194,206,234,244,250]},"region_attributes":{"name":"not_defined","type":"unknown","image_quality":{"good":true,"frontal":true,"good_illumination":true},"shape":"polygon"}},{"shape_attributes":{"name":"polygon","all_points_x":[174,188,213,253,289,339,361,375,353,342,315,302,280,263,241,213,185,165],"all_points_y":[387,403,410,410,403,378,365,391,393,415,413,415,428,432,412,426,426,420]},"region_attributes":{"name":"not_defined","type":"unknown","image_quality":{"good":true,"frontal":true,"good_illumination":true},"shape":"polygon"}},{"shape_attributes":{"name":"polygon","all_points_x":[308,305,328,343,340,328,314],"all_points_y":[455,444,431,431,453,460,460]},"region_attributes":{"name":"not_defined","type":"unknown","image_quality":{"good":true,"frontal":true,"good_illumination":true},"shape":"polygon"}}],"file_attributes":{"caption":"","public_domain":"no","image_url":""}},"Img Captured 104.JPG137544":{"filename":"Img Captured 104.JPG","size":137544,"regions":[{"shape_attributes":{"name":"polygon","all_points_x":[494,447,437,456,474,474,512,542,569,592,593,588,554,514,494],"all_points_y":[301,282,244,231,221,194,177,193,210,219,254,286,310,313,303]},"region_attributes":{"name":"not_defined","type":"unknown","image_quality":{"good":true,"frontal":true,"good_illumination":true},"shape":"polygon"}},{"shape_attributes":{"name":"polygon","all_points_x":[479,452,468,481,503,519,516,512,495,478,465,457,457],"all_points_y":[172,155,126,114,115,130,146,161,164,171,164,159,158]},"region_attributes":{"name":"not_defined","type":"unknown","image_quality":{"good":true,"frontal":true,"good_illumination":true},"shape":"polygon"}},{"shape_attributes":{"name":"polygon","all_points_x":[617,630,664,684,688,683,662,639,627,615],"all_points_y":[210,180,168,183,209,228,234,232,222,216]},"region_attributes":{"name":"not_defined","type":"unknown","image_quality":{"good":true,"frontal":true,"good_illumination":true},"shape":"polygon"}},{"shape_attributes":{"name":"polygon","all_points_x":[668,696,722,726,719,702,674,653],"all_points_y":[332,310,324,348,380,380,379,361]},"region_attributes":{"name":"not_defined","type":"unknown","image_quality":{"good":true,"frontal":true,"good_illumination":true},"shape":"polygon"}},{"shape_attributes":{"name":"polygon","all_points_x":[731,735,742,751,788,792,783,767],"all_points_y":[422,396,374,357,379,398,421,431]},"region_attributes":{"name":"not_defined","type":"unknown","image_quality":{"good":true,"frontal":true,"good_illumination":true},"shape":"polygon"}},{"shape_attributes":{"name":"polygon","all_points_x":[742,763,794,798,783,772,763],"all_points_y":[460,440,444,466,476,487,479]},"region_attributes":{"name":"not_defined","type":"unknown","image_quality":{"good":true,"frontal":true,"good_illumination":true},"shape":"polygon"}},{"shape_attributes":{"name":"polygon","all_points_x":[797,808,823,833,829,813],"all_points_y":[495,476,469,485,500,501]},"region_attributes":{"name":"not_defined","type":"unknown","image_quality":{"good":true,"frontal":true,"good_illumination":true},"shape":"polygon"}},{"shape_attributes":{"name":"polygon","all_points_x":[797,820,840,836,824,797,791,785,797],"all_points_y":[531,519,528,551,561,569,563,550,560]},"region_attributes":{"name":"not_defined","type":"unknown","image_quality":{"good":true,"frontal":true,"good_illumination":true},"shape":"polygon"}},{"shape_attributes":{"name":"polygon","all_points_x":[800,839,867,859,845,827,802,797,804],"all_points_y":[605,585,615,639,658,662,649,645,634]},"region_attributes":{"name":"not_defined","type":"unknown","image_quality":{"good":true,"frontal":true,"good_illumination":true},"shape":"polygon"}},{"shape_attributes":{"name":"polygon","all_points_x":[829,845,867,883,883,864,836,826,820],"all_points_y":[688,666,659,671,712,713,721,707,691]},"region_attributes":{"name":"not_defined","type":"unknown","image_quality":{"good":true,"frontal":true,"good_illumination":true},"shape":"polygon"}},{"shape_attributes":{"name":"polygon","all_points_x":[876,895,914,912,924,949,965,968,957,924,897,876],"all_points_y":[729,710,704,677,666,671,677,707,734,741,738,738]},"region_attributes":{"name":"not_defined","type":"unknown","image_quality":{"good":true,"frontal":true,"good_illumination":true},"shape":"polygon"}},{"shape_attributes":{"name":"polygon","all_points_x":[985,947,940,997,1017,1023,1044,1057,1039,1038,1032,1022],"all_points_y":[395,376,361,365,368,381,381,389,411,421,431,428]},"region_attributes":{"name":"not_defined","type":"unknown","image_quality":{"good":true,"frontal":true,"good_illumination":true},"shape":"polygon"}},{"shape_attributes":{"name":"polygon","all_points_x":[1023,995,976,982,1028],"all_points_y":[710,737,729,685,716]},"region_attributes":{"name":"not_defined","type":"unknown","image_quality":{"good":true,"frontal":true,"good_illumination":true},"shape":"polygon"}},{"shape_attributes":{"name":"polygon","all_points_x":[1022,1023,1052,1064,1096,1125,1155,1147,1130,1121,1089,1073,1068,1055,1045,1025,1016],"all_points_y":[735,713,732,732,741,738,742,761,761,741,751,754,750,744,751,751,748]},"region_attributes":{"name":"not_defined","type":"unknown","image_quality":{"good":true,"frontal":true,"good_illumination":true},"shape":"polygon"}},{"shape_attributes":{"name":"polygon","all_points_x":[1120,1098,1058,1041,1080,1114,1136,1159,1152],"all_points_y":[497,495,474,449,437,438,459,471,516]},"region_attributes":{"name":"not_defined","type":"unknown","image_quality":{"good":true,"frontal":true,"good_illumination":true},"shape":"polygon"}}],"file_attributes":{"caption":"","public_domain":"no","image_url":""}},"Img Captured 102.JPG136784":{"filename":"Img Captured 102.JPG","size":136784,"regions":[{"shape_attributes":{"name":"polygon","all_points_x":[315,277,263,281,307,332,363,372,367,345,310],"all_points_y":[566,541,522,495,465,461,484,515,546,571,568]},"region_attributes":{"name":"not_defined","type":"unknown","image_quality":{"good":true,"frontal":true,"good_illumination":true},"shape":"polygon"}},{"shape_attributes":{"name":"polygon","all_points_x":[495,505,531,553,565,568,546,524,503,495],"all_points_y":[408,386,386,391,416,436,445,455,449,445]},"region_attributes":{"name":"not_defined","type":"unknown","image_quality":{"good":true,"frontal":true,"good_illumination":true},"shape":"polygon"}},{"shape_attributes":{"name":"polygon","all_points_x":[290,280,281,297,329,344,359,363,369,367,342,322,309],"all_points_y":[262,234,195,176,187,187,200,215,231,255,278,280,280]},"region_attributes":{"name":"not_defined","type":"unknown","image_quality":{"good":true,"frontal":true,"good_illumination":true},"shape":"polygon"}},{"shape_attributes":{"name":"polygon","all_points_x":[749,723,685,660,726,790,825,831,825,806,781,768],"all_points_y":[375,350,332,301,309,320,348,367,400,402,408,395]},"region_attributes":{"name":"not_defined","type":"unknown","image_quality":{"good":true,"frontal":true,"good_illumination":true},"shape":"polygon"}},{"shape_attributes":{"name":"polygon","all_points_x":[714,716,702,714,723,735,768,815,815,809,796,784,740,707],"all_points_y":[701,672,634,637,610,585,582,616,653,695,724,730,732,726]},"region_attributes":{"name":"not_defined","type":"unknown","image_quality":{"good":true,"frontal":true,"good_illumination":true},"shape":"polygon"}},{"shape_attributes":{"name":"polygon","all_points_x":[533,495,438,413,401,400,543],"all_points_y":[697,663,656,680,704,732,726]},"region_attributes":{"name":"not_defined","type":"unknown","image_quality":{"good":true,"frontal":true,"good_illumination":true},"shape":"polygon"}},{"shape_attributes":{"name":"polygon","all_points_x":[552,569,582,572],"all_points_y":[310,291,296,316]},"region_attributes":{"name":"not_defined","type":"unknown","image_quality":{"good":true,"frontal":true,"good_illumination":true},"shape":"polygon"}},{"shape_attributes":{"name":"polygon","all_points_x":[644,642,661,664,664,653],"all_points_y":[357,337,337,350,364,370]},"region_attributes":{"name":"not_defined","type":"unknown","image_quality":{"good":true,"frontal":true,"good_illumination":true},"shape":"polygon"}},{"shape_attributes":{"name":"polygon","all_points_x":[650,648,657,667,663],"all_points_y":[402,385,372,386,401]},"region_attributes":{"name":"not_defined","type":"unknown","image_quality":{"good":true,"frontal":true,"good_illumination":true},"shape":"polygon"}},{"shape_attributes":{"name":"polygon","all_points_x":[680,669,692,704,692,678],"all_points_y":[382,367,367,382,386,388]},"region_attributes":{"name":"not_defined","type":"unknown","image_quality":{"good":true,"frontal":true,"good_illumination":true},"shape":"polygon"}},{"shape_attributes":{"name":"polygon","all_points_x":[543,528,539,559,563,552],"all_points_y":[530,520,506,509,525,531]},"region_attributes":{"name":"not_defined","type":"unknown","image_quality":{"good":true,"frontal":true,"good_illumination":true},"shape":"polygon"}},{"shape_attributes":{"name":"polygon","all_points_x":[1428,1421,1441,1447,1447,1437],"all_points_y":[360,344,337,353,361,369]},"region_attributes":{"name":"not_defined","type":"unknown","image_quality":{"good":true,"frontal":true,"good_illumination":true},"shape":"polygon"}},{"shape_attributes":{"name":"polygon","all_points_x":[256,265,275,268,260],"all_points_y":[378,373,382,386,392]},"region_attributes":{"name":"not_defined","type":"unknown","image_quality":{"good":true,"frontal":true,"good_illumination":true},"shape":"polygon"}},{"shape_attributes":{"name":"polygon","all_points_x":[171,173,189,186,174],"all_points_y":[312,300,303,315,316]},"region_attributes":{"name":"not_defined","type":"unknown","image_quality":{"good":true,"frontal":true,"good_illumination":true},"shape":"polygon"}},{"shape_attributes":{"name":"polygon","all_points_x":[211,211,222,227,222],"all_points_y":[225,214,209,215,225]},"region_attributes":{"name":"not_defined","type":"unknown","image_quality":{"good":true,"frontal":true,"good_illumination":true},"shape":"polygon"}}],"file_attributes":{"caption":"","public_domain":"no","image_url":""}},"Img Captured 101.JPG108727":{"filename":"Img Captured 101.JPG","size":108727,"regions":[{"shape_attributes":{"name":"polygon","all_points_x":[560,532,527,535,529,540,547,562,601,638,660,663,644,623,598,579,566],"all_points_y":[297,279,252,216,190,189,162,152,155,176,206,243,291,303,309,310,301]},"region_attributes":{"name":"not_defined","type":"unknown","image_quality":{"good":true,"frontal":true,"good_illumination":true},"shape":"polygon"}},{"shape_attributes":{"name":"polygon","all_points_x":[797,785,788,787,804,815,848,870,867,857,844,829,801],"all_points_y":[221,208,183,137,110,89,91,118,167,206,230,230,225]},"region_attributes":{"name":"not_defined","type":"unknown","image_quality":{"good":true,"frontal":true,"good_illumination":true},"shape":"polygon"}},{"shape_attributes":{"name":"polygon","all_points_x":[328,351,383,411,437,440,426,404,360,347,328],"all_points_y":[556,527,505,516,540,576,605,622,610,597,570]},"region_attributes":{"name":"not_defined","type":"unknown","image_quality":{"good":true,"frontal":true,"good_illumination":true},"shape":"polygon"}},{"shape_attributes":{"name":"polygon","all_points_x":[259,272,290,306,300,287,268],"all_points_y":[475,439,436,461,481,486,484]},"region_attributes":{"name":"not_defined","type":"unknown","image_quality":{"good":true,"frontal":true,"good_illumination":true},"shape":"polygon"}},{"shape_attributes":{"name":"polygon","all_points_x":[369,355,369,383,388,388],"all_points_y":[383,370,360,360,379,383]},"region_attributes":{"name":"not_defined","type":"unknown","image_quality":{"good":true,"frontal":true,"good_illumination":true},"shape":"polygon"}}],"file_attributes":{"caption":"","public_domain":"no","image_url":""}},"Img Captured 100.JPG150241":{"filename":"Img Captured 100.JPG","size":150241,"regions":[{"shape_attributes":{"name":"polygon","all_points_x":[861,840,840,867,881,899,894,888,875,856,846,846],"all_points_y":[632,617,591,579,584,604,621,638,642,633,629,624]},"region_attributes":{"name":"not_defined","type":"unknown","image_quality":{"good":true,"frontal":true,"good_illumination":true},"shape":"polygon"}},{"shape_attributes":{"name":"polygon","all_points_x":[1010,985,985,996,1015,1031,1049,1053,1040,1026],"all_points_y":[617,591,579,562,538,547,566,595,613,623]},"region_attributes":{"name":"not_defined","type":"unknown","image_quality":{"good":true,"frontal":true,"good_illumination":true},"shape":"polygon"}},{"shape_attributes":{"name":"polygon","all_points_x":[1021,1011,1024,1037,1042,1037],"all_points_y":[775,760,745,748,763,776]},"region_attributes":{"name":"not_defined","type":"unknown","image_quality":{"good":true,"frontal":true,"good_illumination":true},"shape":"polygon"}},{"shape_attributes":{"name":"polygon","all_points_x":[923,913,916,926,932,937,937],"all_points_y":[544,538,525,514,524,532,541]},"region_attributes":{"name":"not_defined","type":"unknown","image_quality":{"good":true,"frontal":true,"good_illumination":true},"shape":"polygon"}},{"shape_attributes":{"name":"polygon","all_points_x":[951,940,951,951,980,992,1002,991,975,964],"all_points_y":[487,471,464,451,436,451,474,490,500,500]},"region_attributes":{"name":"not_defined","type":"unknown","image_quality":{"good":true,"frontal":true,"good_illumination":true},"shape":"polygon"}},{"shape_attributes":{"name":"polygon","all_points_x":[938,944,957,969,970,961,956,947],"all_points_y":[376,355,355,357,373,379,390,385]},"region_attributes":{"name":"not_defined","type":"unknown","image_quality":{"good":true,"frontal":true,"good_illumination":true},"shape":"polygon"}}],"file_attributes":{"caption":"","public_domain":"no","image_url":""}},"Img Captured 99.JPG276496":{"filename":"Img Captured 99.JPG","size":276496,"regions":[{"shape_attributes":{"name":"polygon","all_points_x":[746,743,718,730,741,758,756,747],"all_points_y":[216,225,205,190,190,200,215,221]},"region_attributes":{"name":"not_defined","type":"unknown","image_quality":{"good":true,"frontal":true,"good_illumination":true},"shape":"polygon"}},{"shape_attributes":{"name":"polygon","all_points_x":[750,763,777,772,763,752],"all_points_y":[266,263,275,287,293,295]},"region_attributes":{"name":"not_defined","type":"unknown","image_quality":{"good":true,"frontal":true,"good_illumination":true},"shape":"polygon"}},{"shape_attributes":{"name":"polygon","all_points_x":[623,623,626,645,648,651,632,623],"all_points_y":[329,316,309,312,322,339,341,341]},"region_attributes":{"name":"not_defined","type":"unknown","image_quality":{"good":true,"frontal":true,"good_illumination":true},"shape":"polygon"}},{"shape_attributes":{"name":"polygon","all_points_x":[788,784,800,815,820,818,804],"all_points_y":[347,328,320,325,339,350,354]},"region_attributes":{"name":"not_defined","type":"unknown","image_quality":{"good":true,"frontal":true,"good_illumination":true},"shape":"polygon"}},{"shape_attributes":{"name":"polygon","all_points_x":[856,838,845,854,875,883,880,867,853],"all_points_y":[411,399,383,369,379,390,405,410,412]},"region_attributes":{"name":"not_defined","type":"unknown","image_quality":{"good":true,"frontal":true,"good_illumination":true},"shape":"polygon"}},{"shape_attributes":{"name":"polygon","all_points_x":[891,895,908,917,920,916,913,898],"all_points_y":[471,449,448,452,467,477,481,477]},"region_attributes":{"name":"not_defined","type":"unknown","image_quality":{"good":true,"frontal":true,"good_illumination":true},"shape":"polygon"}},{"shape_attributes":{"name":"polygon","all_points_x":[483,478,496,507,519,527,513,502,487],"all_points_y":[484,472,462,462,471,481,497,502,500]},"region_attributes":{"name":"not_defined","type":"unknown","image_quality":{"good":true,"frontal":true,"good_illumination":true},"shape":"polygon"}},{"shape_attributes":{"name":"polygon","all_points_x":[829,806,797,810,841,859,867,854,838,829],"all_points_y":[671,644,617,605,604,613,630,655,671,671]},"region_attributes":{"name":"not_defined","type":"unknown","image_quality":{"good":true,"frontal":true,"good_illumination":true},"shape":"polygon"}},{"shape_attributes":{"name":"polygon","all_points_x":[635,639,627,604,594,636],"all_points_y":[765,737,718,740,762,766]},"region_attributes":{"name":"not_defined","type":"unknown","image_quality":{"good":true,"frontal":true,"good_illumination":true},"shape":"polygon"}},{"shape_attributes":{"name":"polygon","all_points_x":[660,676,687,702,711,698,679,657],"all_points_y":[652,632,626,638,661,671,674,663]},"region_attributes":{"name":"not_defined","type":"unknown","image_quality":{"good":true,"frontal":true,"good_illumination":true},"shape":"polygon"}},{"shape_attributes":{"name":"polygon","all_points_x":[702,714,714,698,684,686],"all_points_y":[624,616,605,598,608,626]},"region_attributes":{"name":"not_defined","type":"unknown","image_quality":{"good":true,"frontal":true,"good_illumination":true},"shape":"polygon"}},{"shape_attributes":{"name":"polygon","all_points_x":[1155,1152,1171,1202,1231,1239,1243,1243,1220,1196,1169],"all_points_y":[443,411,373,357,374,399,427,455,477,481,472]},"region_attributes":{"name":"not_defined","type":"unknown","image_quality":{"good":true,"frontal":true,"good_illumination":true},"shape":"polygon"}},{"shape_attributes":{"name":"polygon","all_points_x":[1131,1132,1144,1150,1150],"all_points_y":[490,474,469,478,494]},"region_attributes":{"name":"not_defined","type":"unknown","image_quality":{"good":true,"frontal":true,"good_illumination":true},"shape":"polygon"}},{"shape_attributes":{"name":"polygon","all_points_x":[1267,1283,1296,1296,1296,1267,1255],"all_points_y":[461,440,439,455,477,486,490]},"region_attributes":{"name":"not_defined","type":"unknown","image_quality":{"good":true,"frontal":true,"good_illumination":true},"shape":"polygon"}},{"shape_attributes":{"name":"polygon","all_points_x":[1050,1060,1068,1069,1056,1046],"all_points_y":[733,724,733,743,753,747]},"region_attributes":{"name":"not_defined","type":"unknown","image_quality":{"good":true,"frontal":true,"good_illumination":true},"shape":"polygon"}},{"shape_attributes":{"name":"polygon","all_points_x":[1104,1094,1100,1114,1128,1141,1133,1122],"all_points_y":[565,554,543,535,541,560,569,575]},"region_attributes":{"name":"not_defined","type":"unknown","image_quality":{"good":true,"frontal":true,"good_illumination":true},"shape":"polygon"}}],"file_attributes":{"caption":"","public_domain":"no","image_url":""}},"Img Captured 98.JPG277132":{"filename":"Img Captured 98.JPG","size":277132,"regions":[{"shape_attributes":{"name":"polygon","all_points_x":[419,400,382,357,345,348,357,364,382,412,444,470,488,495,498,470,443,430,412],"all_points_y":[569,545,514,460,432,412,368,335,320,335,349,384,437,489,529,561,571,574,574]},"region_attributes":{"name":"not_defined","type":"unknown","image_quality":{"good":true,"frontal":true,"good_illumination":true},"shape":"polygon"}},{"shape_attributes":{"name":"polygon","all_points_x":[422,434,432,421,411,416,424,460,489,492,489,479,456,431,421,419],"all_points_y":[236,224,195,163,146,116,105,112,154,223,250,265,277,272,261,249]},"region_attributes":{"name":"not_defined","type":"unknown","image_quality":{"good":true,"frontal":true,"good_illumination":true},"shape":"polygon"}},{"shape_attributes":{"name":"polygon","all_points_x":[514,526,537,546,537,526,513,513],"all_points_y":[597,593,590,604,617,619,604,598]},"region_attributes":{"name":"not_defined","type":"unknown","image_quality":{"good":true,"frontal":true,"good_illumination":true},"shape":"polygon"}},{"shape_attributes":{"name":"polygon","all_points_x":[1041,1006,986,989,999,1005,1027,1076,1117,1134,1137,1134,1124,1101,1108,1101,1086,1069,1038],"all_points_y":[743,719,677,641,631,607,574,566,594,633,663,683,696,689,714,732,746,738,743]},"region_attributes":{"name":"not_defined","type":"unknown","image_quality":{"good":true,"frontal":true,"good_illumination":true},"shape":"polygon"}},{"shape_attributes":{"name":"polygon","all_points_x":[804,850,865,853,839,820,814,820,823,810,791,797],"all_points_y":[619,626,619,600,578,571,581,594,612,612,620,614]},"region_attributes":{"name":"not_defined","type":"unknown","image_quality":{"good":true,"frontal":true,"good_illumination":true},"shape":"polygon"}},{"shape_attributes":{"name":"polygon","all_points_x":[965,974,986,990,981,967,964],"all_points_y":[331,322,325,333,354,345,345]},"region_attributes":{"name":"not_defined","type":"unknown","image_quality":{"good":true,"frontal":true,"good_illumination":true},"shape":"polygon"}},{"shape_attributes":{"name":"polygon","all_points_x":[990,984,999,1005,1011,1009,1009,1003,1002],"all_points_y":[293,284,280,265,268,285,291,299,303]},"region_attributes":{"name":"not_defined","type":"unknown","image_quality":{"good":true,"frontal":true,"good_illumination":true},"shape":"polygon"}},{"shape_attributes":{"name":"polygon","all_points_x":[303,293,303,316,324,323,320,308],"all_points_y":[167,159,144,143,150,165,169,174]},"region_attributes":{"name":"not_defined","type":"unknown","image_quality":{"good":true,"frontal":true,"good_illumination":true},"shape":"polygon"}},{"shape_attributes":{"name":"polygon","all_points_x":[360,355,369,378,391,392,379,370],"all_points_y":[152,146,133,128,139,159,166,163]},"region_attributes":{"name":"not_defined","type":"unknown","image_quality":{"good":true,"frontal":true,"good_illumination":true},"shape":"polygon"}},{"shape_attributes":{"name":"polygon","all_points_x":[429,431,431,416,415,424],"all_points_y":[292,285,279,278,288,294]},"region_attributes":{"name":"not_defined","type":"unknown","image_quality":{"good":true,"frontal":true,"good_illumination":true},"shape":"polygon"}},{"shape_attributes":{"name":"polygon","all_points_x":[501,513,520,514,506,501],"all_points_y":[345,341,347,358,355,351]},"region_attributes":{"name":"not_defined","type":"unknown","image_quality":{"good":true,"frontal":true,"good_illumination":true},"shape":"polygon"}},{"shape_attributes":{"name":"polygon","all_points_x":[471,477,480,481,481,474],"all_points_y":[315,302,306,312,315,315]},"region_attributes":{"name":"not_defined","type":"unknown","image_quality":{"good":true,"frontal":true,"good_illumination":true},"shape":"polygon"}},{"shape_attributes":{"name":"polygon","all_points_x":[490,496,505,509,503],"all_points_y":[319,309,309,317,325]},"region_attributes":{"name":"not_defined","type":"unknown","image_quality":{"good":true,"frontal":true,"good_illumination":true},"shape":"polygon"}},{"shape_attributes":{"name":"polygon","all_points_x":[502,507,513,515,515,507],"all_points_y":[290,282,282,288,295,298]},"region_attributes":{"name":"not_defined","type":"unknown","image_quality":{"good":true,"frontal":true,"good_illumination":true},"shape":"polygon"}},{"shape_attributes":{"name":"polygon","all_points_x":[507,507,514,523,519,515,515],"all_points_y":[182,172,169,177,184,185,186]},"region_attributes":{"name":"not_defined","type":"unknown","image_quality":{"good":true,"frontal":true,"good_illumination":true},"shape":"polygon"}},{"shape_attributes":{"name":"polygon","all_points_x":[520,517,521,530,543,548,553,545,535,529],"all_points_y":[158,146,133,128,130,140,149,161,167,165]},"region_attributes":{"name":"not_defined","type":"unknown","image_quality":{"good":true,"frontal":true,"good_illumination":true},"shape":"polygon"}},{"shape_attributes":{"name":"polygon","all_points_x":[532,538,548,550,548,540,537],"all_points_y":[93,83,87,95,103,102,102]},"region_attributes":{"name":"not_defined","type":"unknown","image_quality":{"good":true,"frontal":true,"good_illumination":true},"shape":"polygon"}},{"shape_attributes":{"name":"polygon","all_points_x":[370,381,384,378],"all_points_y":[221,218,225,233]},"region_attributes":{"name":"not_defined","type":"unknown","image_quality":{"good":true,"frontal":true,"good_illumination":true},"shape":"polygon"}},{"shape_attributes":{"name":"polygon","all_points_x":[340,340,352,355,353,345,342],"all_points_y":[50,48,45,51,58,59,58]},"region_attributes":{"name":"not_defined","type":"unknown","image_quality":{"good":true,"frontal":true,"good_illumination":true},"shape":"polygon"}},{"shape_attributes":{"name":"polygon","all_points_x":[389,394,403,404,394,387],"all_points_y":[203,188,196,217,216,213]},"region_attributes":{"name":"not_defined","type":"unknown","image_quality":{"good":true,"frontal":true,"good_illumination":true},"shape":"polygon"}},{"shape_attributes":{"name":"polygon","all_points_x":[400,397,402,408,408,405],"all_points_y":[156,146,144,149,153,158]},"region_attributes":{"name":"not_defined","type":"unknown","image_quality":{"good":true,"frontal":true,"good_illumination":true},"shape":"polygon"}},{"shape_attributes":{"name":"polygon","all_points_x":[348,349,353,365,367,356,347,339],"all_points_y":[92,82,80,87,100,112,106,101]},"region_attributes":{"name":"not_defined","type":"unknown","image_quality":{"good":true,"frontal":true,"good_illumination":true},"shape":"polygon"}},{"shape_attributes":{"name":"polygon","all_points_x":[326,331,339,341,337,334],"all_points_y":[127,116,116,122,128,130]},"region_attributes":{"name":"not_defined","type":"unknown","image_quality":{"good":true,"frontal":true,"good_illumination":true},"shape":"polygon"}},{"shape_attributes":{"name":"polygon","all_points_x":[392,394,409,417,415,414,413],"all_points_y":[298,277,276,276,294,306,308]},"region_attributes":{"name":"not_defined","type":"unknown","image_quality":{"good":true,"frontal":true,"good_illumination":true},"shape":"polygon"}}],"file_attributes":{"caption":"","public_domain":"no","image_url":""}},"Img Captured 97.JPG235764":{"filename":"Img Captured 97.JPG","size":235764,"regions":[{"shape_attributes":{"name":"polygon","all_points_x":[612,604,595,598,586,595,618,634,640,649,647,617],"all_points_y":[139,130,130,118,115,95,76,83,95,105,126,140]},"region_attributes":{"name":"not_defined","type":"unknown","image_quality":{"good":true,"frontal":true,"good_illumination":true},"shape":"polygon"}},{"shape_attributes":{"name":"polygon","all_points_x":[627,618,614,593,611,621,649,666,671,665,684,677,672,653,642],"all_points_y":[612,623,615,615,592,558,557,567,567,576,586,601,612,620,612]},"region_attributes":{"name":"not_defined","type":"unknown","image_quality":{"good":true,"frontal":true,"good_illumination":true},"shape":"polygon"}}],"file_attributes":{"caption":"","public_domain":"no","image_url":""}},"Img Captured 96.JPG248625":{"filename":"Img Captured 96.JPG","size":248625,"regions":[{"shape_attributes":{"name":"polygon","all_points_x":[654,641,644,651,665,677,677,673,664],"all_points_y":[215,202,184,176,176,189,203,212,216]},"region_attributes":{"name":"not_defined","type":"unknown","image_quality":{"good":true,"frontal":true,"good_illumination":true},"shape":"polygon"}},{"shape_attributes":{"name":"polygon","all_points_x":[629,632,641,652,673,680,674,660,645,632],"all_points_y":[357,336,320,314,329,354,370,385,380,374]},"region_attributes":{"name":"not_defined","type":"unknown","image_quality":{"good":true,"frontal":true,"good_illumination":true},"shape":"polygon"}},{"shape_attributes":{"name":"polygon","all_points_x":[627,616,627,641,651,654,644,636],"all_points_y":[437,423,402,404,412,433,443,445]},"region_attributes":{"name":"not_defined","type":"unknown","image_quality":{"good":true,"frontal":true,"good_illumination":true},"shape":"polygon"}},{"shape_attributes":{"name":"polygon","all_points_x":[610,626,622,622,641,657,664,668,663,648,627,614,611],"all_points_y":[557,544,527,505,505,513,532,553,581,591,592,585,578]},"region_attributes":{"name":"not_defined","type":"unknown","image_quality":{"good":true,"frontal":true,"good_illumination":true},"shape":"polygon"}},{"shape_attributes":{"name":"polygon","all_points_x":[627,630,645,668,670,668,654,635],"all_points_y":[703,673,670,674,696,718,718,718]},"region_attributes":{"name":"not_defined","type":"unknown","image_quality":{"good":true,"frontal":true,"good_illumination":true},"shape":"polygon"}},{"shape_attributes":{"name":"polygon","all_points_x":[689,680,690,711,731,737,734,728,714,698],"all_points_y":[491,474,456,452,462,474,493,502,509,503]},"region_attributes":{"name":"not_defined","type":"unknown","image_quality":{"good":true,"frontal":true,"good_illumination":true},"shape":"polygon"}},{"shape_attributes":{"name":"polygon","all_points_x":[600,604,610,670,671,655,620,603],"all_points_y":[83,53,45,60,88,114,117,117]},"region_attributes":{"name":"not_defined","type":"unknown","image_quality":{"good":true,"frontal":true,"good_illumination":true},"shape":"polygon"}},{"shape_attributes":{"name":"polygon","all_points_x":[1123,1120,1135,1139,1139,1131],"all_points_y":[282,275,275,287,295,300]},"region_attributes":{"name":"not_defined","type":"unknown","image_quality":{"good":true,"frontal":true,"good_illumination":true},"shape":"polygon"}}],"file_attributes":{"caption":"","public_domain":"no","image_url":""}},"Img Captured 95.JPG185977":{"filename":"Img Captured 95.JPG","size":185977,"regions":[{"shape_attributes":{"name":"polygon","all_points_x":[292,297,314,346,381,405,419,422,421,402,387,352,322,292],"all_points_y":[723,609,608,579,574,601,646,677,710,732,750,753,741,723]},"region_attributes":{"name":"not_defined","type":"unknown","image_quality":{"good":true,"frontal":true,"good_illumination":true},"shape":"polygon"}},{"shape_attributes":{"name":"polygon","all_points_x":[536,532,551,548,532,514,498,523,532,539,588,623,643,649,627,612,579,560,552],"all_points_y":[481,459,431,406,390,386,367,349,351,336,341,364,412,466,487,513,523,514,510]},"region_attributes":{"name":"not_defined","type":"unknown","image_quality":{"good":true,"frontal":true,"good_illumination":true},"shape":"polygon"}},{"shape_attributes":{"name":"polygon","all_points_x":[649,634,664,704,680,680,664,665,688,725,747,764,780,779,766,742,690,652,649],"all_points_y":[244,216,193,161,146,132,127,110,114,114,117,146,191,243,263,279,279,259,248]},"region_attributes":{"name":"not_defined","type":"unknown","image_quality":{"good":true,"frontal":true,"good_illumination":true},"shape":"polygon"}},{"shape_attributes":{"name":"polygon","all_points_x":[526,524,529,541,560,562,547,529,525],"all_points_y":[666,653,646,649,658,676,692,687,680]},"region_attributes":{"name":"not_defined","type":"unknown","image_quality":{"good":true,"frontal":true,"good_illumination":true},"shape":"polygon"}},{"shape_attributes":{"name":"polygon","all_points_x":[596,596,604,616,619,610,593],"all_points_y":[648,638,629,637,657,667,665]},"region_attributes":{"name":"not_defined","type":"unknown","image_quality":{"good":true,"frontal":true,"good_illumination":true},"shape":"polygon"}},{"shape_attributes":{"name":"polygon","all_points_x":[474,486,498,499,500,498,486,476,473],"all_points_y":[750,744,746,754,767,773,772,765,762]},"region_attributes":{"name":"not_defined","type":"unknown","image_quality":{"good":true,"frontal":true,"good_illumination":true},"shape":"polygon"}},{"shape_attributes":{"name":"polygon","all_points_x":[453,461,468,468,460,456],"all_points_y":[732,717,725,735,739,739]},"region_attributes":{"name":"not_defined","type":"unknown","image_quality":{"good":true,"frontal":true,"good_illumination":true},"shape":"polygon"}},{"shape_attributes":{"name":"polygon","all_points_x":[495,508,516,521,521,510,498],"all_points_y":[614,599,599,612,627,628,628]},"region_attributes":{"name":"not_defined","type":"unknown","image_quality":{"good":true,"frontal":true,"good_illumination":true},"shape":"polygon"}},{"shape_attributes":{"name":"polygon","all_points_x":[500,509,514,519,516,509,501],"all_points_y":[550,538,541,549,563,563,559]},"region_attributes":{"name":"not_defined","type":"unknown","image_quality":{"good":true,"frontal":true,"good_illumination":true},"shape":"polygon"}},{"shape_attributes":{"name":"polygon","all_points_x":[549,556,561,565,559,552,547],"all_points_y":[590,588,588,595,603,602,590]},"region_attributes":{"name":"not_defined","type":"unknown","image_quality":{"good":true,"frontal":true,"good_illumination":true},"shape":"polygon"}},{"shape_attributes":{"name":"polygon","all_points_x":[596,583,609,623,625,619,616],"all_points_y":[577,568,571,578,588,593,593]},"region_attributes":{"name":"not_defined","type":"unknown","image_quality":{"good":true,"frontal":true,"good_illumination":true},"shape":"polygon"}},{"shape_attributes":{"name":"polygon","all_points_x":[635,638,646,652,666,666,660,643,638],"all_points_y":[554,544,547,538,546,558,566,565,563]},"region_attributes":{"name":"not_defined","type":"unknown","image_quality":{"good":true,"frontal":true,"good_illumination":true},"shape":"polygon"}},{"shape_attributes":{"name":"polygon","all_points_x":[842,829,825,844,857,869,858,892,912,914,902,883,867,858,861,861,851,848,847],"all_points_y":[428,415,403,400,382,371,362,354,377,401,415,410,401,403,423,436,440,443,445]},"region_attributes":{"name":"not_defined","type":"unknown","image_quality":{"good":true,"frontal":true,"good_illumination":true},"shape":"polygon"}},{"shape_attributes":{"name":"polygon","all_points_x":[934,946,959,962,959,941],"all_points_y":[381,368,373,383,394,400]},"region_attributes":{"name":"not_defined","type":"unknown","image_quality":{"good":true,"frontal":true,"good_illumination":true},"shape":"polygon"}}],"file_attributes":{"caption":"","public_domain":"no","image_url":""}},"Img Captured 94.JPG136345":{"filename":"Img Captured 94.JPG","size":136345,"regions":[{"shape_attributes":{"name":"polygon","all_points_x":[763,750,722,737,745,776,842,877,900,908,890,889],"all_points_y":[751,713,666,567,535,522,551,598,674,737,780,782]},"region_attributes":{"name":"not_defined","type":"unknown","image_quality":{"good":true,"frontal":true,"good_illumination":true},"shape":"polygon"}},{"shape_attributes":{"name":"polygon","all_points_x":[808,824,821,821,808,808,802,829,858,880,897,896,887,867,849,827,817,817],"all_points_y":[421,406,380,358,326,294,262,251,270,301,360,386,433,444,459,455,446,444]},"region_attributes":{"name":"not_defined","type":"unknown","image_quality":{"good":true,"frontal":true,"good_illumination":true},"shape":"polygon"}},{"shape_attributes":{"name":"polygon","all_points_x":[780,804,829,843,874,899,911,899,884,859,821,786,772],"all_points_y":[159,126,121,98,98,132,189,216,227,241,228,206,189]},"region_attributes":{"name":"not_defined","type":"unknown","image_quality":{"good":true,"frontal":true,"good_illumination":true},"shape":"polygon"}},{"shape_attributes":{"name":"polygon","all_points_x":[660,661,668,682,683,682,670,665],"all_points_y":[53,38,36,45,58,67,70,65]},"region_attributes":{"name":"not_defined","type":"unknown","image_quality":{"good":true,"frontal":true,"good_illumination":true},"shape":"polygon"}},{"shape_attributes":{"name":"polygon","all_points_x":[714,726,728,723,715,714],"all_points_y":[182,185,192,199,199,194]},"region_attributes":{"name":"not_defined","type":"unknown","image_quality":{"good":true,"frontal":true,"good_illumination":true},"shape":"polygon"}},{"shape_attributes":{"name":"polygon","all_points_x":[714,719,720,734,744,739,730,723,723],"all_points_y":[248,243,234,230,244,256,260,258,256]},"region_attributes":{"name":"not_defined","type":"unknown","image_quality":{"good":true,"frontal":true,"good_illumination":true},"shape":"polygon"}},{"shape_attributes":{"name":"polygon","all_points_x":[668,658,658,665,681,690,688,683,677,678],"all_points_y":[334,324,315,306,306,317,329,336,337,334]},"region_attributes":{"name":"not_defined","type":"unknown","image_quality":{"good":true,"frontal":true,"good_illumination":true},"shape":"polygon"}},{"shape_attributes":{"name":"polygon","all_points_x":[740,733,742,750,762,773,771,762,748],"all_points_y":[313,308,293,284,288,300,313,323,323]},"region_attributes":{"name":"not_defined","type":"unknown","image_quality":{"good":true,"frontal":true,"good_illumination":true},"shape":"polygon"}},{"shape_attributes":{"name":"polygon","all_points_x":[963,971,976,982,983,975,967,965],"all_points_y":[125,118,115,124,132,140,138,136]},"region_attributes":{"name":"not_defined","type":"unknown","image_quality":{"good":true,"frontal":true,"good_illumination":true},"shape":"polygon"}},{"shape_attributes":{"name":"polygon","all_points_x":[973,968,970,978,980,982,981,981],"all_points_y":[69,80,85,88,82,85,78,72]},"region_attributes":{"name":"not_defined","type":"unknown","image_quality":{"good":true,"frontal":true,"good_illumination":true},"shape":"polygon"}},{"shape_attributes":{"name":"polygon","all_points_x":[1003,1010,1014,1015,1009,997,989,989,988,990,993,1002],"all_points_y":[156,158,166,175,184,188,180,171,164,157,153,154]},"region_attributes":{"name":"not_defined","type":"unknown","image_quality":{"good":true,"frontal":true,"good_illumination":true},"shape":"polygon"}},{"shape_attributes":{"name":"polygon","all_points_x":[1041,1048,1056,1059,1058,1055,1048,1044,1042],"all_points_y":[151,143,143,152,161,167,170,169,168]},"region_attributes":{"name":"not_defined","type":"unknown","image_quality":{"good":true,"frontal":true,"good_illumination":true},"shape":"polygon"}},{"shape_attributes":{"name":"polygon","all_points_x":[945,949,951,959,969,965,959,952,950],"all_points_y":[239,233,230,229,238,248,252,251,248]},"region_attributes":{"name":"not_defined","type":"unknown","image_quality":{"good":true,"frontal":true,"good_illumination":true},"shape":"polygon"}},{"shape_attributes":{"name":"polygon","all_points_x":[929,933,930,945,959,964,968,966,961,949,937,931],"all_points_y":[310,299,295,283,283,293,302,314,324,329,324,319]},"region_attributes":{"name":"not_defined","type":"unknown","image_quality":{"good":true,"frontal":true,"good_illumination":true},"shape":"polygon"}},{"shape_attributes":{"name":"polygon","all_points_x":[914,924,930,932,928,917,916],"all_points_y":[340,335,338,344,354,351,349]},"region_attributes":{"name":"not_defined","type":"unknown","image_quality":{"good":true,"frontal":true,"good_illumination":true},"shape":"polygon"}},{"shape_attributes":{"name":"polygon","all_points_x":[899,896,906,913,916,917,909,906],"all_points_y":[519,513,502,501,509,516,524,524]},"region_attributes":{"name":"not_defined","type":"unknown","image_quality":{"good":true,"frontal":true,"good_illumination":true},"shape":"polygon"}},{"shape_attributes":{"name":"polygon","all_points_x":[909,914,920,924,925,924,917,913],"all_points_y":[481,470,470,475,481,485,488,487]},"region_attributes":{"name":"not_defined","type":"unknown","image_quality":{"good":true,"frontal":true,"good_illumination":true},"shape":"polygon"}},{"shape_attributes":{"name":"polygon","all_points_x":[873,873,877,884,885,883,873],"all_points_y":[511,500,498,499,507,512,513]},"region_attributes":{"name":"not_defined","type":"unknown","image_quality":{"good":true,"frontal":true,"good_illumination":true},"shape":"polygon"}},{"shape_attributes":{"name":"polygon","all_points_x":[909,914,924,926,924,917,911],"all_points_y":[551,543,543,551,559,560,557]},"region_attributes":{"name":"not_defined","type":"unknown","image_quality":{"good":true,"frontal":true,"good_illumination":true},"shape":"polygon"}},{"shape_attributes":{"name":"polygon","all_points_x":[807,809,817,823,823,819,810,809],"all_points_y":[476,468,467,471,478,485,484,483]},"region_attributes":{"name":"not_defined","type":"unknown","image_quality":{"good":true,"frontal":true,"good_illumination":true},"shape":"polygon"}},{"shape_attributes":{"name":"polygon","all_points_x":[790,793,794,802,802,802,796,795],"all_points_y":[358,349,348,351,356,363,365,364]},"region_attributes":{"name":"not_defined","type":"unknown","image_quality":{"good":true,"frontal":true,"good_illumination":true},"shape":"polygon"}},{"shape_attributes":{"name":"polygon","all_points_x":[781,786,790,793,790,784,783],"all_points_y":[308,306,308,313,319,320,320]},"region_attributes":{"name":"not_defined","type":"unknown","image_quality":{"good":true,"frontal":true,"good_illumination":true},"shape":"polygon"}},{"shape_attributes":{"name":"polygon","all_points_x":[750,757,765,766,762,754],"all_points_y":[400,391,394,403,410,407]},"region_attributes":{"name":"not_defined","type":"unknown","image_quality":{"good":true,"frontal":true,"good_illumination":true},"shape":"polygon"}},{"shape_attributes":{"name":"polygon","all_points_x":[1044,1036,1055,1063,1062,1058],"all_points_y":[99,91,94,102,107,113]},"region_attributes":{"name":"not_defined","type":"unknown","image_quality":{"good":true,"frontal":true,"good_illumination":true},"shape":"polygon"}},{"shape_attributes":{"name":"polygon","all_points_x":[1003,1009,1015,1019,1017,1007],"all_points_y":[112,105,104,110,115,119]},"region_attributes":{"name":"not_defined","type":"unknown","image_quality":{"good":true,"frontal":true,"good_illumination":true},"shape":"polygon"}}],"file_attributes":{"caption":"","public_domain":"no","image_url":""}},"Img Captured 93.JPG194062":{"filename":"Img Captured 93.JPG","size":194062,"regions":[{"shape_attributes":{"name":"polygon","all_points_x":[602,586,590,599,600,624,631,631,625,614],"all_points_y":[770,757,742,731,720,721,742,762,772,777]},"region_attributes":{"name":"not_defined","type":"unknown","image_quality":{"good":true,"frontal":true,"good_illumination":true},"shape":"polygon"}},{"shape_attributes":{"name":"polygon","all_points_x":[379,386,398,404,406,401,395],"all_points_y":[788,775,772,775,788,798,801]},"region_attributes":{"name":"not_defined","type":"unknown","image_quality":{"good":true,"frontal":true,"good_illumination":true},"shape":"polygon"}},{"shape_attributes":{"name":"polygon","all_points_x":[464,465,480,483,492,492,486,468],"all_points_y":[662,649,641,642,660,673,682,675]},"region_attributes":{"name":"not_defined","type":"unknown","image_quality":{"good":true,"frontal":true,"good_illumination":true},"shape":"polygon"}},{"shape_attributes":{"name":"polygon","all_points_x":[625,615,620,611,621,638,661,678,678,666,650,637],"all_points_y":[601,590,575,554,529,520,535,562,583,608,621,624]},"region_attributes":{"name":"not_defined","type":"unknown","image_quality":{"good":true,"frontal":true,"good_illumination":true},"shape":"polygon"}},{"shape_attributes":{"name":"polygon","all_points_x":[640,640,650,672,686,690,668,661,643],"all_points_y":[474,447,431,429,447,470,496,499,500]},"region_attributes":{"name":"not_defined","type":"unknown","image_quality":{"good":true,"frontal":true,"good_illumination":true},"shape":"polygon"}},{"shape_attributes":{"name":"polygon","all_points_x":[589,581,589,608,632,635,635,619,599,587],"all_points_y":[476,456,441,431,444,469,483,500,507,500]},"region_attributes":{"name":"not_defined","type":"unknown","image_quality":{"good":true,"frontal":true,"good_illumination":true},"shape":"polygon"}},{"shape_attributes":{"name":"polygon","all_points_x":[621,617,627,641,663,671,672,652,638,619],"all_points_y":[387,364,349,343,353,378,402,416,421,414]},"region_attributes":{"name":"not_defined","type":"unknown","image_quality":{"good":true,"frontal":true,"good_illumination":true},"shape":"polygon"}},{"shape_attributes":{"name":"polygon","all_points_x":[642,637,649,659,669,667,660,659],"all_points_y":[720,716,701,689,700,715,728,732]},"region_attributes":{"name":"not_defined","type":"unknown","image_quality":{"good":true,"frontal":true,"good_illumination":true},"shape":"polygon"}},{"shape_attributes":{"name":"polygon","all_points_x":[622,616,630,638,643,630],"all_points_y":[676,661,659,671,684,686]},"region_attributes":{"name":"not_defined","type":"unknown","image_quality":{"good":true,"frontal":true,"good_illumination":true},"shape":"polygon"}},{"shape_attributes":{"name":"polygon","all_points_x":[661,651,650,666,671,672,671],"all_points_y":[315,308,296,292,303,315,319]},"region_attributes":{"name":"not_defined","type":"unknown","image_quality":{"good":true,"frontal":true,"good_illumination":true},"shape":"polygon"}},{"shape_attributes":{"name":"polygon","all_points_x":[670,671,677,681,688,689,689,689,686,676],"all_points_y":[219,207,195,186,197,213,223,224,236,234]},"region_attributes":{"name":"not_defined","type":"unknown","image_quality":{"good":true,"frontal":true,"good_illumination":true},"shape":"polygon"}},{"shape_attributes":{"name":"polygon","all_points_x":[636,642,658,664,662,660,649,646],"all_points_y":[99,90,79,93,101,103,108,112]},"region_attributes":{"name":"not_defined","type":"unknown","image_quality":{"good":true,"frontal":true,"good_illumination":true},"shape":"polygon"}},{"shape_attributes":{"name":"polygon","all_points_x":[935,940,943,945,953,952,946,938],"all_points_y":[625,614,607,604,622,633,634,633]},"region_attributes":{"name":"not_defined","type":"unknown","image_quality":{"good":true,"frontal":true,"good_illumination":true},"shape":"polygon"}},{"shape_attributes":{"name":"polygon","all_points_x":[892,899,907,908,899,895],"all_points_y":[573,572,572,581,586,590]},"region_attributes":{"name":"not_defined","type":"unknown","image_quality":{"good":true,"frontal":true,"good_illumination":true},"shape":"polygon"}}],"file_attributes":{"caption":"","public_domain":"no","image_url":""}}}